{
  "version": "v4",
  "repo": "borisyankov/DefinitelyTyped",
  "ref": "master",
  "path": "typings",
  "bundle": "typings/tsd.d.ts",
  "installed": {
    "jquery/jquery.d.ts": {
      "commit": "36c6ce86fb64bafb28ec95dc78c6b98228b45c8d"
    },
    "jquery.dataTables/jquery.dataTables.d.ts": {
      "commit": "36c6ce86fb64bafb28ec95dc78c6b98228b45c8d"
    },
    "moment/moment.d.ts": {
      "commit": "36c6ce86fb64bafb28ec95dc78c6b98228b45c8d"
    },
    "moment/moment-node.d.ts": {
      "commit": "36c6ce86fb64bafb28ec95dc78c6b98228b45c8d"
    }
  }
}
